README.rst
setup.cfg
setup.py
joli_users/__init__.py
joli_users/admin.py
joli_users/apps.py
joli_users/tests.py
joli_users/urls.py
joli_users.egg-info/PKG-INFO
joli_users.egg-info/SOURCES.txt
joli_users.egg-info/dependency_links.txt
joli_users.egg-info/requires.txt
joli_users.egg-info/top_level.txt
joli_users/migrations/__init__.py
joli_users/models/__init__.py
joli_users/models/models.py
joli_users/models/user_photos.py
joli_users/models/user_profile.py
joli_users/serializers/__init__.py
joli_users/serializers/user_photo_serializer.py
joli_users/serializers/user_profile_serializer.py
joli_users/serializers/user_serializer.py
joli_users/views/__init__.py
joli_users/views/authenticate_view.py
joli_users/views/user_photos_view.py
joli_users/views/user_profile_view.py
joli_users/views/user_registration_view.py
joli_users/views/user_view.py