Metadata-Version: 1.1
Name: joli-users
Version: 0.1
Summary: Joli Users is a django rest framework module for creating and managing users for mobile clients.
Home-page: https://www.joli_users.jolinkomo.com/
Author: jolinkomo
Author-email: developer@jolinkomo.com
License: BSD License
Platform: UNKNOWN
Classifier: Environment :: Web Environment
Classifier: Framework :: Django
Classifier: Intended Audience :: Developers
Classifier: License :: OSI Approved :: BSD License
Classifier: Operating System :: OS Independent
Classifier: Programming Language :: Python
Classifier: Programming Language :: Python :: 3
Classifier: Programming Language :: Python :: 3.4
Classifier: Programming Language :: Python :: 3.5
Classifier: Topic :: Internet :: WWW/HTTP
Classifier: Topic :: Internet :: WWW/HTTP :: Dynamic Content
